imio.smartweb.locales-1.1.36-py3.12-nspkg.pth
imio/smartweb/locales/__init__.py
imio/smartweb/locales/configure.zcml
imio/smartweb/locales/locales/collective-schedulefield.pot
imio/smartweb/locales/locales/imio.smartweb.pot
imio/smartweb/locales/locales/plone-manual.pot
imio/smartweb/locales/locales/widgets.pot
imio/smartweb/locales/locales/de/LC_MESSAGES/imio.smartweb.po
imio/smartweb/locales/locales/de/LC_MESSAGES/plone.po
imio/smartweb/locales/locales/de/LC_MESSAGES/widgets.po
imio/smartweb/locales/locales/fr/LC_MESSAGES/imio.smartweb.po
imio/smartweb/locales/locales/fr/LC_MESSAGES/plone.po
imio/smartweb/locales/locales/fr/LC_MESSAGES/widgets.po
imio/smartweb/locales/locales/nl/LC_MESSAGES/imio.smartweb.po
imio/smartweb/locales/locales/nl/LC_MESSAGES/plone.po
imio/smartweb/locales/locales/nl/LC_MESSAGES/widgets.po
imio_smartweb_locales-1.1.36.dist-info/licenses/LICENSE.GPL
imio_smartweb_locales-1.1.36.dist-info/licenses/LICENSE.rst
imio_smartweb_locales-1.1.36.dist-info/METADATA
imio_smartweb_locales-1.1.36.dist-info/WHEEL
imio_smartweb_locales-1.1.36.dist-info/namespace_packages.txt
imio_smartweb_locales-1.1.36.dist-info/top_level.txt
imio_smartweb_locales-1.1.36.dist-info/RECORD
