Metadata-Version: 2.4
Name: imio.smartweb.locales
Version: 1.1.36
Summary: Locales for iMio smartweb packages
Home-page: https://github.com/imio/imio.smartweb.locales
Author: iMio
Author-email: christophe.boulanger@imio.be
License: GPL version 2
Project-URL: PyPI, https://pypi.python.org/pypi/imio.smartweb.locales
Project-URL: Source, https://github.com/imio/imio.smartweb.locales
Project-URL: Tracker, https://github.com/imio/imio.smartweb.locales/issues
Keywords: Python Plone CMS
Classifier: Environment :: Web Environment
Classifier: Framework :: Plone
Classifier: Framework :: Plone :: Addon
Classifier: Framework :: Plone :: 5.2
Classifier: Framework :: Plone :: 6.0
Classifier: Framework :: Plone :: 6.1
Classifier: Programming Language :: Python
Classifier: Programming Language :: Python :: 3
Classifier: Programming Language :: Python :: 3.10
Classifier: Programming Language :: Python :: 3.11
Classifier: Programming Language :: Python :: 3.12
Classifier: Programming Language :: Python :: 3.13
Classifier: Operating System :: OS Independent
Classifier: License :: OSI Approved :: GNU General Public License v2 (GPLv2)
Requires-Python: >=3.10
License-File: LICENSE.GPL
License-File: LICENSE.rst
Requires-Dist: setuptools
Dynamic: author
Dynamic: author-email
Dynamic: classifier
Dynamic: description
Dynamic: home-page
Dynamic: keywords
Dynamic: license
Dynamic: license-file
Dynamic: project-url
Dynamic: requires-dist
Dynamic: requires-python
Dynamic: summary
